{
  "version": "0.3.3",
  "flags": {},
  "shapes": [
    {
      "label": "potato",
      "text": "",
      "points": [
        [
          44.0,
          320.0
        ],
        [
          39.0,
          320.0
        ],
        [
          37.0,
          322.0
        ],
        [
          37.0,
          323.0
        ],
        [
          36.0,
          324.0
        ],
        [
          36.0,
          326.0
        ],
        [
          35.0,
          327.0
        ],
        [
          35.0,
          329.0
        ],
        [
          34.0,
          330.0
        ],
        [
          34.0,
          333.0
        ],
        [
          33.0,
          334.0
        ],
        [
          33.0,
          336.0
        ],
        [
          30.0,
          339.0
        ],
        [
          30.0,
          340.0
        ],
        [
          29.0,
          341.0
        ],
        [
          29.0,
          343.0
        ],
        [
          24.0,
          348.0
        ],
        [
          23.0,
          348.0
        ],
        [
          21.0,
          350.0
        ],
        [
          19.0,
          350.0
        ],
        [
          18.0,
          351.0
        ],
        [
          17.0,
          351.0
        ],
        [
          16.0,
          352.0
        ],
        [
          16.0,
          357.0
        ],
        [
          15.0,
          358.0
        ],
        [
          15.0,
          368.0
        ],
        [
          16.0,
          369.0
        ],
        [
          16.0,
          371.0
        ],
        [
          17.0,
          372.0
        ],
        [
          17.0,
          374.0
        ],
        [
          18.0,
          375.0
        ],
        [
          18.0,
          377.0
        ],
        [
          19.0,
          378.0
        ],
        [
          19.0,
          379.0
        ],
        [
          20.0,
          380.0
        ],
        [
          20.0,
          381.0
        ],
        [
          21.0,
          382.0
        ],
        [
          21.0,
          383.0
        ],
        [
          22.0,
          384.0
        ],
        [
          22.0,
          385.0
        ],
        [
          23.0,
          386.0
        ],
        [
          23.0,
          387.0
        ],
        [
          26.0,
          390.0
        ],
        [
          27.0,
          390.0
        ],
        [
          28.0,
          391.0
        ],
        [
          31.0,
          391.0
        ],
        [
          36.0,
          386.0
        ],
        [
          36.0,
          385.0
        ],
        [
          40.0,
          381.0
        ],
        [
          41.0,
          381.0
        ],
        [
          42.0,
          380.0
        ],
        [
          43.0,
          380.0
        ],
        [
          45.0,
          378.0
        ],
        [
          46.0,
          378.0
        ],
        [
          48.0,
          376.0
        ],
        [
          48.0,
          375.0
        ],
        [
          50.0,
          373.0
        ],
        [
          52.0,
          373.0
        ],
        [
          53.0,
          372.0
        ],
        [
          54.0,
          372.0
        ],
        [
          55.0,
          373.0
        ],
        [
          56.0,
          373.0
        ],
        [
          57.0,
          374.0
        ],
        [
          58.0,
          374.0
        ],
        [
          59.0,
          373.0
        ],
        [
          60.0,
          373.0
        ],
        [
          65.0,
          368.0
        ],
        [
          65.0,
          367.0
        ],
        [
          66.0,
          366.0
        ],
        [
          66.0,
          365.0
        ],
        [
          69.0,
          362.0
        ],
        [
          69.0,
          359.0
        ],
        [
          70.0,
          358.0
        ],
        [
          70.0,
          356.0
        ],
        [
          69.0,
          355.0
        ],
        [
          69.0,
          352.0
        ],
        [
          67.0,
          350.0
        ],
        [
          66.0,
          350.0
        ],
        [
          65.0,
          349.0
        ],
        [
          64.0,
          349.0
        ],
        [
          61.0,
          346.0
        ],
        [
          61.0,
          345.0
        ],
        [
          60.0,
          344.0
        ],
        [
          60.0,
          340.0
        ],
        [
          59.0,
          339.0
        ],
        [
          59.0,
          336.0
        ],
        [
          58.0,
          335.0
        ],
        [
          58.0,
          333.0
        ],
        [
          56.0,
          331.0
        ],
        [
          54.0,
          331.0
        ],
        [
          53.0,
          330.0
        ],
        [
          51.0,
          330.0
        ],
        [
          50.0,
          329.0
        ],
        [
          49.0,
          329.0
        ],
        [
          48.0,
          328.0
        ],
        [
          48.0,
          327.0
        ],
        [
          47.0,
          326.0
        ],
        [
          47.0,
          325.0
        ],
        [
          46.0,
          324.0
        ],
        [
          46.0,
          322.0
        ]
      ],
      "group_id": null,
      "shape_type": "polygon",
      "flags": {}
    },
    {
      "label": "potato",
      "text": "",
      "points": [
        [
          327.0,
          200.0
        ],
        [
          315.0,
          200.0
        ],
        [
          314.0,
          199.0
        ],
        [
          313.0,
          199.0
        ],
        [
          312.0,
          198.0
        ],
        [
          310.0,
          198.0
        ],
        [
          309.0,
          199.0
        ],
        [
          308.0,
          199.0
        ],
        [
          305.0,
          202.0
        ],
        [
          304.0,
          201.0
        ],
        [
          303.0,
          201.0
        ],
        [
          301.0,
          199.0
        ],
        [
          296.0,
          199.0
        ],
        [
          294.0,
          201.0
        ],
        [
          294.0,
          202.0
        ],
        [
          293.0,
          203.0
        ],
        [
          293.0,
          212.0
        ],
        [
          292.0,
          213.0
        ],
        [
          292.0,
          215.0
        ],
        [
          291.0,
          216.0
        ],
        [
          291.0,
          220.0
        ],
        [
          292.0,
          221.0
        ],
        [
          292.0,
          222.0
        ],
        [
          293.0,
          223.0
        ],
        [
          293.0,
          225.0
        ],
        [
          294.0,
          226.0
        ],
        [
          294.0,
          229.0
        ],
        [
          295.0,
          230.0
        ],
        [
          294.0,
          231.0
        ],
        [
          294.0,
          232.0
        ],
        [
          291.0,
          235.0
        ],
        [
          286.0,
          235.0
        ],
        [
          285.0,
          236.0
        ],
        [
          282.0,
          236.0
        ],
        [
          280.0,
          238.0
        ],
        [
          280.0,
          242.0
        ],
        [
          281.0,
          243.0
        ],
        [
          281.0,
          244.0
        ],
        [
          282.0,
          245.0
        ],
        [
          282.0,
          246.0
        ],
        [
          285.0,
          249.0
        ],
        [
          286.0,
          249.0
        ],
        [
          287.0,
          250.0
        ],
        [
          287.0,
          251.0
        ],
        [
          288.0,
          252.0
        ],
        [
          289.0,
          252.0
        ],
        [
          291.0,
          254.0
        ],
        [
          292.0,
          254.0
        ],
        [
          293.0,
          255.0
        ],
        [
          296.0,
          255.0
        ],
        [
          297.0,
          256.0
        ],
        [
          300.0,
          256.0
        ],
        [
          301.0,
          257.0
        ],
        [
          302.0,
          257.0
        ],
        [
          303.0,
          258.0
        ],
        [
          303.0,
          259.0
        ],
        [
          304.0,
          260.0
        ],
        [
          304.0,
          261.0
        ],
        [
          303.0,
          262.0
        ],
        [
          303.0,
          264.0
        ],
        [
          304.0,
          265.0
        ],
        [
          304.0,
          267.0
        ],
        [
          305.0,
          268.0
        ],
        [
          305.0,
          269.0
        ],
        [
          306.0,
          269.0
        ],
        [
          307.0,
          270.0
        ],
        [
          312.0,
          270.0
        ],
        [
          313.0,
          269.0
        ],
        [
          314.0,
          269.0
        ],
        [
          322.0,
          261.0
        ],
        [
          322.0,
          260.0
        ],
        [
          325.0,
          257.0
        ],
        [
          325.0,
          251.0
        ],
        [
          324.0,
          250.0
        ],
        [
          324.0,
          248.0
        ],
        [
          323.0,
          247.0
        ],
        [
          323.0,
          244.0
        ],
        [
          326.0,
          241.0
        ],
        [
          327.0,
          241.0
        ],
        [
          328.0,
          240.0
        ],
        [
          331.0,
          240.0
        ],
        [
          340.0,
          231.0
        ],
        [
          340.0,
          230.0
        ],
        [
          341.0,
          229.0
        ],
        [
          341.0,
          228.0
        ],
        [
          342.0,
          227.0
        ],
        [
          342.0,
          224.0
        ],
        [
          343.0,
          223.0
        ],
        [
          343.0,
          222.0
        ],
        [
          336.0,
          215.0
        ],
        [
          336.0,
          214.0
        ],
        [
          335.0,
          213.0
        ],
        [
          335.0,
          209.0
        ],
        [
          334.0,
          208.0
        ],
        [
          334.0,
          207.0
        ],
        [
          333.0,
          206.0
        ],
        [
          333.0,
          205.0
        ],
        [
          331.0,
          203.0
        ],
        [
          331.0,
          202.0
        ],
        [
          330.0,
          201.0
        ],
        [
          328.0,
          201.0
        ]
      ],
      "group_id": null,
      "shape_type": "polygon",
      "flags": {}
    },
    {
      "label": "potato",
      "text": "",
      "points": [
        [
          267.0,
          521.0
        ],
        [
          265.0,
          523.0
        ],
        [
          265.0,
          530.0
        ],
        [
          267.0,
          534.0
        ],
        [
          273.0,
          541.0
        ],
        [
          273.0,
          544.0
        ],
        [
          274.0,
          545.0
        ],
        [
          274.0,
          547.0
        ],
        [
          280.0,
          550.0
        ],
        [
          282.0,
          552.0
        ],
        [
          283.0,
          561.0
        ],
        [
          291.0,
          569.0
        ],
        [
          292.0,
          569.0
        ],
        [
          293.0,
          571.0
        ],
        [
          297.0,
          575.0
        ],
        [
          297.0,
          578.0
        ],
        [
          295.0,
          580.0
        ],
        [
          294.0,
          580.0
        ],
        [
          293.0,
          582.0
        ],
        [
          293.0,
          587.0
        ],
        [
          294.0,
          588.0
        ],
        [
          294.0,
          591.0
        ],
        [
          290.0,
          594.0
        ],
        [
          290.0,
          599.0
        ],
        [
          289.0,
          600.0
        ],
        [
          289.0,
          604.0
        ],
        [
          290.0,
          605.0
        ],
        [
          290.0,
          607.0
        ],
        [
          291.0,
          607.0
        ],
        [
          293.0,
          609.0
        ],
        [
          303.0,
          609.0
        ],
        [
          304.0,
          608.0
        ],
        [
          308.0,
          608.0
        ],
        [
          312.0,
          616.0
        ],
        [
          317.0,
          619.0
        ],
        [
          318.0,
          621.0
        ],
        [
          318.0,
          624.0
        ],
        [
          320.0,
          627.0
        ],
        [
          320.0,
          629.0
        ],
        [
          324.0,
          632.0
        ],
        [
          326.0,
          632.0
        ],
        [
          329.0,
          634.0
        ],
        [
          332.0,
          634.0
        ],
        [
          333.0,
          635.0
        ],
        [
          335.0,
          635.0
        ],
        [
          337.0,
          633.0
        ],
        [
          338.0,
          631.0
        ],
        [
          338.0,
          629.0
        ],
        [
          339.0,
          628.0
        ],
        [
          339.0,
          626.0
        ],
        [
          340.0,
          625.0
        ],
        [
          340.0,
          620.0
        ],
        [
          341.0,
          619.0
        ],
        [
          341.0,
          607.0
        ],
        [
          342.0,
          606.0
        ],
        [
          345.0,
          606.0
        ],
        [
          346.0,
          607.0
        ],
        [
          350.0,
          607.0
        ],
        [
          351.0,
          606.0
        ],
        [
          353.0,
          606.0
        ],
        [
          355.0,
          605.0
        ],
        [
          361.0,
          600.0
        ],
        [
          362.0,
          600.0
        ],
        [
          365.0,
          597.0
        ],
        [
          365.0,
          595.0
        ],
        [
          366.0,
          594.0
        ],
        [
          366.0,
          592.0
        ],
        [
          367.0,
          590.0
        ],
        [
          369.0,
          588.0
        ],
        [
          371.0,
          587.0
        ],
        [
          373.0,
          587.0
        ],
        [
          376.0,
          584.0
        ],
        [
          376.0,
          577.0
        ],
        [
          375.0,
          576.0
        ],
        [
          375.0,
          574.0
        ],
        [
          373.0,
          572.0
        ],
        [
          371.0,
          572.0
        ],
        [
          370.0,
          571.0
        ],
        [
          366.0,
          571.0
        ],
        [
          365.0,
          572.0
        ],
        [
          356.0,
          572.0
        ],
        [
          355.0,
          571.0
        ],
        [
          355.0,
          568.0
        ],
        [
          364.0,
          559.0
        ],
        [
          364.0,
          557.0
        ],
        [
          365.0,
          556.0
        ],
        [
          365.0,
          554.0
        ],
        [
          367.0,
          550.0
        ],
        [
          367.0,
          547.0
        ],
        [
          365.0,
          544.0
        ],
        [
          365.0,
          537.0
        ],
        [
          363.0,
          533.0
        ],
        [
          361.0,
          531.0
        ],
        [
          356.0,
          531.0
        ],
        [
          351.0,
          534.0
        ],
        [
          343.0,
          534.0
        ],
        [
          342.0,
          535.0
        ],
        [
          339.0,
          532.0
        ],
        [
          339.0,
          522.0
        ],
        [
          340.0,
          521.0
        ],
        [
          340.0,
          519.0
        ],
        [
          341.0,
          518.0
        ],
        [
          341.0,
          516.0
        ],
        [
          342.0,
          514.0
        ],
        [
          341.0,
          512.0
        ],
        [
          340.0,
          512.0
        ],
        [
          336.0,
          509.0
        ],
        [
          329.0,
          510.0
        ],
        [
          325.0,
          512.0
        ],
        [
          322.0,
          515.0
        ],
        [
          321.0,
          518.0
        ],
        [
          319.0,
          520.0
        ],
        [
          317.0,
          520.0
        ],
        [
          316.0,
          521.0
        ],
        [
          314.0,
          520.0
        ],
        [
          307.0,
          520.0
        ],
        [
          305.0,
          521.0
        ],
        [
          300.0,
          526.0
        ],
        [
          297.0,
          526.0
        ],
        [
          296.0,
          525.0
        ],
        [
          292.0,
          525.0
        ],
        [
          288.0,
          529.0
        ],
        [
          286.0,
          530.0
        ],
        [
          282.0,
          528.0
        ],
        [
          281.0,
          526.0
        ],
        [
          278.0,
          523.0
        ],
        [
          274.0,
          521.0
        ]
      ],
      "group_id": null,
      "shape_type": "polygon",
      "flags": {}
    },
    {
      "label": "potato",
      "text": "",
      "points": [
        [
          585.0,
          96.0
        ],
        [
          584.0,
          97.0
        ],
        [
          581.0,
          97.0
        ],
        [
          579.0,
          99.0
        ],
        [
          579.0,
          100.0
        ],
        [
          577.0,
          102.0
        ],
        [
          577.0,
          105.0
        ],
        [
          576.0,
          106.0
        ],
        [
          576.0,
          109.0
        ],
        [
          574.0,
          111.0
        ],
        [
          563.0,
          111.0
        ],
        [
          562.0,
          112.0
        ],
        [
          561.0,
          112.0
        ],
        [
          559.0,
          114.0
        ],
        [
          559.0,
          115.0
        ],
        [
          558.0,
          116.0
        ],
        [
          558.0,
          125.0
        ],
        [
          556.0,
          127.0
        ],
        [
          555.0,
          127.0
        ],
        [
          551.0,
          131.0
        ],
        [
          551.0,
          136.0
        ],
        [
          552.0,
          137.0
        ],
        [
          552.0,
          138.0
        ],
        [
          553.0,
          139.0
        ],
        [
          554.0,
          139.0
        ],
        [
          555.0,
          140.0
        ],
        [
          557.0,
          140.0
        ],
        [
          558.0,
          141.0
        ],
        [
          560.0,
          141.0
        ],
        [
          563.0,
          144.0
        ],
        [
          564.0,
          144.0
        ],
        [
          565.0,
          143.0
        ],
        [
          566.0,
          143.0
        ],
        [
          568.0,
          145.0
        ],
        [
          568.0,
          146.0
        ],
        [
          569.0,
          147.0
        ],
        [
          569.0,
          148.0
        ],
        [
          573.0,
          152.0
        ],
        [
          573.0,
          153.0
        ],
        [
          574.0,
          154.0
        ],
        [
          575.0,
          154.0
        ],
        [
          576.0,
          155.0
        ],
        [
          580.0,
          155.0
        ],
        [
          585.0,
          150.0
        ],
        [
          585.0,
          148.0
        ],
        [
          586.0,
          147.0
        ],
        [
          586.0,
          141.0
        ],
        [
          587.0,
          140.0
        ],
        [
          587.0,
          138.0
        ],
        [
          590.0,
          135.0
        ],
        [
          590.0,
          134.0
        ],
        [
          591.0,
          133.0
        ],
        [
          591.0,
          132.0
        ],
        [
          596.0,
          127.0
        ],
        [
          598.0,
          127.0
        ],
        [
          599.0,
          126.0
        ],
        [
          601.0,
          126.0
        ],
        [
          602.0,
          125.0
        ],
        [
          604.0,
          125.0
        ],
        [
          606.0,
          123.0
        ],
        [
          606.0,
          122.0
        ],
        [
          607.0,
          121.0
        ],
        [
          607.0,
          119.0
        ],
        [
          606.0,
          118.0
        ],
        [
          606.0,
          117.0
        ],
        [
          604.0,
          117.0
        ],
        [
          603.0,
          116.0
        ],
        [
          601.0,
          116.0
        ],
        [
          600.0,
          115.0
        ],
        [
          599.0,
          115.0
        ],
        [
          598.0,
          114.0
        ],
        [
          597.0,
          114.0
        ],
        [
          596.0,
          113.0
        ],
        [
          595.0,
          113.0
        ],
        [
          594.0,
          112.0
        ],
        [
          593.0,
          112.0
        ],
        [
          590.0,
          109.0
        ],
        [
          590.0,
          100.0
        ],
        [
          587.0,
          97.0
        ],
        [
          586.0,
          97.0
        ]
      ],
      "group_id": null,
      "shape_type": "polygon",
      "flags": {}
    },
    {
      "label": "potato",
      "text": "",
      "points": [
        [
          516.0,
          256.0
        ],
        [
          514.0,
          258.0
        ],
        [
          514.0,
          261.0
        ],
        [
          515.0,
          262.0
        ],
        [
          515.0,
          263.0
        ],
        [
          516.0,
          264.0
        ],
        [
          516.0,
          265.0
        ],
        [
          518.0,
          268.0
        ],
        [
          518.0,
          270.0
        ],
        [
          521.0,
          273.0
        ],
        [
          522.0,
          273.0
        ],
        [
          523.0,
          274.0
        ],
        [
          526.0,
          275.0
        ],
        [
          528.0,
          277.0
        ],
        [
          528.0,
          283.0
        ],
        [
          527.0,
          284.0
        ],
        [
          527.0,
          289.0
        ],
        [
          529.0,
          291.0
        ],
        [
          530.0,
          291.0
        ],
        [
          532.0,
          293.0
        ],
        [
          533.0,
          293.0
        ],
        [
          534.0,
          294.0
        ],
        [
          537.0,
          294.0
        ],
        [
          538.0,
          293.0
        ],
        [
          539.0,
          293.0
        ],
        [
          541.0,
          291.0
        ],
        [
          545.0,
          291.0
        ],
        [
          549.0,
          295.0
        ],
        [
          549.0,
          296.0
        ],
        [
          550.0,
          297.0
        ],
        [
          550.0,
          301.0
        ],
        [
          551.0,
          302.0
        ],
        [
          551.0,
          313.0
        ],
        [
          552.0,
          314.0
        ],
        [
          552.0,
          316.0
        ],
        [
          553.0,
          317.0
        ],
        [
          553.0,
          318.0
        ],
        [
          554.0,
          318.0
        ],
        [
          555.0,
          319.0
        ],
        [
          557.0,
          319.0
        ],
        [
          558.0,
          320.0
        ],
        [
          559.0,
          320.0
        ],
        [
          560.0,
          321.0
        ],
        [
          561.0,
          321.0
        ],
        [
          564.0,
          323.0
        ],
        [
          570.0,
          323.0
        ],
        [
          571.0,
          322.0
        ],
        [
          572.0,
          322.0
        ],
        [
          573.0,
          321.0
        ],
        [
          574.0,
          321.0
        ],
        [
          575.0,
          320.0
        ],
        [
          578.0,
          319.0
        ],
        [
          581.0,
          316.0
        ],
        [
          582.0,
          316.0
        ],
        [
          587.0,
          311.0
        ],
        [
          588.0,
          311.0
        ],
        [
          589.0,
          310.0
        ],
        [
          592.0,
          310.0
        ],
        [
          593.0,
          309.0
        ],
        [
          595.0,
          309.0
        ],
        [
          596.0,
          308.0
        ],
        [
          598.0,
          308.0
        ],
        [
          600.0,
          306.0
        ],
        [
          601.0,
          306.0
        ],
        [
          602.0,
          305.0
        ],
        [
          602.0,
          300.0
        ],
        [
          601.0,
          299.0
        ],
        [
          601.0,
          298.0
        ],
        [
          598.0,
          295.0
        ],
        [
          597.0,
          295.0
        ],
        [
          593.0,
          291.0
        ],
        [
          593.0,
          290.0
        ],
        [
          592.0,
          289.0
        ],
        [
          593.0,
          288.0
        ],
        [
          593.0,
          282.0
        ],
        [
          595.0,
          280.0
        ],
        [
          596.0,
          280.0
        ],
        [
          597.0,
          279.0
        ],
        [
          602.0,
          279.0
        ],
        [
          603.0,
          278.0
        ],
        [
          604.0,
          278.0
        ],
        [
          606.0,
          276.0
        ],
        [
          606.0,
          267.0
        ],
        [
          603.0,
          264.0
        ],
        [
          602.0,
          264.0
        ],
        [
          601.0,
          263.0
        ],
        [
          597.0,
          263.0
        ],
        [
          596.0,
          262.0
        ],
        [
          595.0,
          262.0
        ],
        [
          588.0,
          255.0
        ],
        [
          588.0,
          254.0
        ],
        [
          584.0,
          250.0
        ],
        [
          583.0,
          250.0
        ],
        [
          582.0,
          249.0
        ],
        [
          580.0,
          249.0
        ],
        [
          579.0,
          248.0
        ],
        [
          577.0,
          248.0
        ],
        [
          576.0,
          249.0
        ],
        [
          572.0,
          249.0
        ],
        [
          571.0,
          248.0
        ],
        [
          570.0,
          248.0
        ],
        [
          568.0,
          246.0
        ],
        [
          562.0,
          246.0
        ],
        [
          561.0,
          247.0
        ],
        [
          557.0,
          247.0
        ],
        [
          555.0,
          249.0
        ],
        [
          555.0,
          255.0
        ],
        [
          557.0,
          258.0
        ],
        [
          557.0,
          263.0
        ],
        [
          556.0,
          264.0
        ],
        [
          556.0,
          265.0
        ],
        [
          554.0,
          267.0
        ],
        [
          553.0,
          267.0
        ],
        [
          552.0,
          268.0
        ],
        [
          549.0,
          267.0
        ],
        [
          543.0,
          261.0
        ],
        [
          542.0,
          261.0
        ],
        [
          541.0,
          260.0
        ],
        [
          540.0,
          260.0
        ],
        [
          537.0,
          258.0
        ],
        [
          535.0,
          258.0
        ],
        [
          534.0,
          257.0
        ],
        [
          532.0,
          257.0
        ],
        [
          531.0,
          256.0
        ],
        [
          530.0,
          256.0
        ],
        [
          527.0,
          254.0
        ],
        [
          521.0,
          254.0
        ],
        [
          520.0,
          255.0
        ],
        [
          518.0,
          255.0
        ],
        [
          517.0,
          256.0
        ]
      ],
      "group_id": null,
      "shape_type": "polygon",
      "flags": {}
    },
    {
      "label": "weed",
      "text": "",
      "points": [
        [
          72.0,
          535.0
        ],
        [
          72.0,
          537.0
        ],
        [
          73.0,
          538.0
        ],
        [
          73.0,
          539.0
        ],
        [
          74.0,
          540.0
        ],
        [
          75.0,
          540.0
        ],
        [
          76.0,
          541.0
        ],
        [
          80.0,
          541.0
        ],
        [
          81.0,
          542.0
        ],
        [
          83.0,
          542.0
        ],
        [
          84.0,
          543.0
        ],
        [
          86.0,
          543.0
        ],
        [
          87.0,
          544.0
        ],
        [
          88.0,
          544.0
        ],
        [
          89.0,
          545.0
        ],
        [
          90.0,
          545.0
        ],
        [
          91.0,
          546.0
        ],
        [
          92.0,
          546.0
        ],
        [
          93.0,
          547.0
        ],
        [
          94.0,
          547.0
        ],
        [
          95.0,
          548.0
        ],
        [
          97.0,
          548.0
        ],
        [
          98.0,
          549.0
        ],
        [
          100.0,
          549.0
        ],
        [
          101.0,
          550.0
        ],
        [
          102.0,
          550.0
        ],
        [
          103.0,
          551.0
        ],
        [
          107.0,
          551.0
        ],
        [
          108.0,
          552.0
        ],
        [
          115.0,
          552.0
        ],
        [
          116.0,
          553.0
        ],
        [
          131.0,
          553.0
        ],
        [
          132.0,
          554.0
        ],
        [
          134.0,
          554.0
        ],
        [
          135.0,
          555.0
        ],
        [
          136.0,
          555.0
        ],
        [
          137.0,
          556.0
        ],
        [
          144.0,
          556.0
        ],
        [
          144.0,
          552.0
        ],
        [
          143.0,
          551.0
        ],
        [
          142.0,
          551.0
        ],
        [
          141.0,
          550.0
        ],
        [
          139.0,
          550.0
        ],
        [
          138.0,
          549.0
        ],
        [
          136.0,
          549.0
        ],
        [
          135.0,
          548.0
        ],
        [
          132.0,
          548.0
        ],
        [
          131.0,
          547.0
        ],
        [
          130.0,
          547.0
        ],
        [
          129.0,
          546.0
        ],
        [
          127.0,
          546.0
        ],
        [
          126.0,
          545.0
        ],
        [
          123.0,
          545.0
        ],
        [
          122.0,
          544.0
        ],
        [
          119.0,
          544.0
        ],
        [
          118.0,
          543.0
        ],
        [
          115.0,
          543.0
        ],
        [
          114.0,
          542.0
        ],
        [
          112.0,
          542.0
        ],
        [
          111.0,
          541.0
        ],
        [
          110.0,
          541.0
        ],
        [
          109.0,
          540.0
        ],
        [
          108.0,
          540.0
        ],
        [
          107.0,
          539.0
        ],
        [
          104.0,
          539.0
        ],
        [
          103.0,
          538.0
        ],
        [
          100.0,
          538.0
        ],
        [
          99.0,
          537.0
        ],
        [
          95.0,
          537.0
        ],
        [
          94.0,
          536.0
        ],
        [
          92.0,
          536.0
        ],
        [
          91.0,
          535.0
        ],
        [
          89.0,
          535.0
        ],
        [
          88.0,
          534.0
        ],
        [
          86.0,
          534.0
        ],
        [
          85.0,
          533.0
        ],
        [
          81.0,
          533.0
        ],
        [
          80.0,
          532.0
        ],
        [
          77.0,
          532.0
        ],
        [
          76.0,
          531.0
        ],
        [
          75.0,
          532.0
        ],
        [
          73.0,
          532.0
        ],
        [
          73.0,
          534.0
        ]
      ],
      "group_id": null,
      "shape_type": "polygon",
      "flags": {}
    },
    {
      "label": "weed",
      "text": "",
      "points": [
        [
          595.0,
          28.0
        ],
        [
          594.0,
          27.0
        ],
        [
          592.0,
          27.0
        ],
        [
          591.0,
          26.0
        ],
        [
          588.0,
          26.0
        ],
        [
          587.0,
          25.0
        ],
        [
          581.0,
          25.0
        ],
        [
          580.0,
          26.0
        ],
        [
          579.0,
          26.0
        ],
        [
          568.0,
          37.0
        ],
        [
          567.0,
          37.0
        ],
        [
          566.0,
          38.0
        ],
        [
          565.0,
          38.0
        ],
        [
          564.0,
          39.0
        ],
        [
          562.0,
          39.0
        ],
        [
          560.0,
          41.0
        ],
        [
          559.0,
          41.0
        ],
        [
          558.0,
          42.0
        ],
        [
          558.0,
          43.0
        ],
        [
          556.0,
          45.0
        ],
        [
          556.0,
          46.0
        ],
        [
          555.0,
          47.0
        ],
        [
          555.0,
          49.0
        ],
        [
          554.0,
          50.0
        ],
        [
          554.0,
          51.0
        ],
        [
          555.0,
          52.0
        ],
        [
          555.0,
          55.0
        ],
        [
          558.0,
          58.0
        ],
        [
          561.0,
          58.0
        ],
        [
          562.0,
          59.0
        ],
        [
          567.0,
          59.0
        ],
        [
          568.0,
          58.0
        ],
        [
          569.0,
          58.0
        ],
        [
          573.0,
          54.0
        ],
        [
          574.0,
          54.0
        ],
        [
          576.0,
          52.0
        ],
        [
          577.0,
          52.0
        ],
        [
          579.0,
          50.0
        ],
        [
          580.0,
          50.0
        ],
        [
          581.0,
          49.0
        ],
        [
          585.0,
          49.0
        ],
        [
          586.0,
          48.0
        ],
        [
          589.0,
          48.0
        ],
        [
          595.0,
          42.0
        ],
        [
          595.0,
          41.0
        ],
        [
          596.0,
          40.0
        ],
        [
          596.0,
          37.0
        ],
        [
          597.0,
          36.0
        ],
        [
          597.0,
          32.0
        ],
        [
          596.0,
          31.0
        ],
        [
          596.0,
          30.0
        ],
        [
          595.0,
          29.0
        ]
      ],
      "group_id": null,
      "shape_type": "polygon",
      "flags": {}
    },
    {
      "label": "weed",
      "text": "",
      "points": [
        [
          154.0,
          235.0
        ],
        [
          152.0,
          237.0
        ],
        [
          151.0,
          237.0
        ],
        [
          151.0,
          238.0
        ],
        [
          149.0,
          240.0
        ],
        [
          149.0,
          241.0
        ],
        [
          148.0,
          242.0
        ],
        [
          148.0,
          245.0
        ],
        [
          147.0,
          246.0
        ],
        [
          147.0,
          249.0
        ],
        [
          148.0,
          250.0
        ],
        [
          148.0,
          252.0
        ],
        [
          149.0,
          253.0
        ],
        [
          149.0,
          254.0
        ],
        [
          150.0,
          255.0
        ],
        [
          151.0,
          255.0
        ],
        [
          152.0,
          256.0
        ],
        [
          160.0,
          256.0
        ],
        [
          161.0,
          255.0
        ],
        [
          162.0,
          255.0
        ],
        [
          164.0,
          253.0
        ],
        [
          164.0,
          242.0
        ],
        [
          163.0,
          241.0
        ],
        [
          163.0,
          240.0
        ],
        [
          158.0,
          235.0
        ]
      ],
      "group_id": null,
      "shape_type": "polygon",
      "flags": {}
    },
    {
      "label": "weed",
      "text": "",
      "points": [
        [
          42.0,
          211.0
        ],
        [
          33.0,
          211.0
        ],
        [
          32.0,
          212.0
        ],
        [
          31.0,
          212.0
        ],
        [
          28.0,
          215.0
        ],
        [
          28.0,
          217.0
        ],
        [
          27.0,
          218.0
        ],
        [
          27.0,
          221.0
        ],
        [
          26.0,
          222.0
        ],
        [
          26.0,
          224.0
        ],
        [
          27.0,
          225.0
        ],
        [
          27.0,
          238.0
        ],
        [
          28.0,
          239.0
        ],
        [
          28.0,
          243.0
        ],
        [
          29.0,
          244.0
        ],
        [
          29.0,
          245.0
        ],
        [
          32.0,
          248.0
        ],
        [
          33.0,
          248.0
        ],
        [
          34.0,
          249.0
        ],
        [
          36.0,
          249.0
        ],
        [
          38.0,
          247.0
        ],
        [
          38.0,
          246.0
        ],
        [
          39.0,
          245.0
        ],
        [
          39.0,
          243.0
        ],
        [
          40.0,
          242.0
        ],
        [
          40.0,
          241.0
        ],
        [
          41.0,
          240.0
        ],
        [
          41.0,
          239.0
        ],
        [
          42.0,
          238.0
        ],
        [
          42.0,
          237.0
        ],
        [
          43.0,
          236.0
        ],
        [
          43.0,
          235.0
        ],
        [
          44.0,
          234.0
        ],
        [
          44.0,
          232.0
        ],
        [
          45.0,
          231.0
        ],
        [
          45.0,
          229.0
        ],
        [
          46.0,
          228.0
        ],
        [
          46.0,
          219.0
        ],
        [
          45.0,
          218.0
        ],
        [
          45.0,
          216.0
        ],
        [
          44.0,
          215.0
        ],
        [
          44.0,
          214.0
        ],
        [
          43.0,
          213.0
        ],
        [
          43.0,
          212.0
        ]
      ],
      "group_id": null,
      "shape_type": "polygon",
      "flags": {}
    },
    {
      "label": "weed",
      "text": "",
      "points": [
        [
          322.0,
          283.0
        ],
        [
          320.0,
          285.0
        ],
        [
          320.0,
          286.0
        ],
        [
          319.0,
          287.0
        ],
        [
          319.0,
          291.0
        ],
        [
          318.0,
          292.0
        ],
        [
          318.0,
          301.0
        ],
        [
          319.0,
          302.0
        ],
        [
          319.0,
          304.0
        ],
        [
          320.0,
          305.0
        ],
        [
          320.0,
          311.0
        ],
        [
          321.0,
          312.0
        ],
        [
          321.0,
          315.0
        ],
        [
          324.0,
          318.0
        ],
        [
          326.0,
          318.0
        ],
        [
          330.0,
          314.0
        ],
        [
          330.0,
          313.0
        ],
        [
          331.0,
          312.0
        ],
        [
          331.0,
          311.0
        ],
        [
          332.0,
          310.0
        ],
        [
          332.0,
          305.0
        ],
        [
          333.0,
          304.0
        ],
        [
          333.0,
          299.0
        ],
        [
          332.0,
          298.0
        ],
        [
          332.0,
          293.0
        ],
        [
          331.0,
          292.0
        ],
        [
          331.0,
          290.0
        ],
        [
          330.0,
          289.0
        ],
        [
          330.0,
          288.0
        ],
        [
          325.0,
          283.0
        ]
      ],
      "group_id": null,
      "shape_type": "polygon",
      "flags": {}
    }
  ],
  "imagePath": "..\\after_crop\\tile_10_9.jpg",
  "imageData": null,
  "imageHeight": 640,
  "imageWidth": 640
}