{
  "version": "0.3.3",
  "flags": {},
  "shapes": [
    {
      "label": "potato",
      "text": "",
      "points": [
        [
          38.0,
          423.0
        ],
        [
          37.0,
          424.0
        ],
        [
          37.0,
          425.0
        ],
        [
          36.0,
          426.0
        ],
        [
          36.0,
          427.0
        ],
        [
          35.0,
          428.0
        ],
        [
          35.0,
          429.0
        ],
        [
          33.0,
          431.0
        ],
        [
          33.0,
          432.0
        ],
        [
          31.0,
          434.0
        ],
        [
          31.0,
          435.0
        ],
        [
          30.0,
          436.0
        ],
        [
          30.0,
          439.0
        ],
        [
          29.0,
          440.0
        ],
        [
          29.0,
          441.0
        ],
        [
          27.0,
          443.0
        ],
        [
          27.0,
          444.0
        ],
        [
          23.0,
          448.0
        ],
        [
          22.0,
          448.0
        ],
        [
          18.0,
          452.0
        ],
        [
          18.0,
          453.0
        ],
        [
          17.0,
          454.0
        ],
        [
          12.0,
          454.0
        ],
        [
          11.0,
          455.0
        ],
        [
          10.0,
          455.0
        ],
        [
          6.0,
          459.0
        ],
        [
          6.0,
          460.0
        ],
        [
          4.0,
          462.0
        ],
        [
          4.0,
          463.0
        ],
        [
          2.0,
          465.0
        ],
        [
          1.0,
          465.0
        ],
        [
          0.0,
          466.0
        ],
        [
          0.0,
          477.0
        ],
        [
          1.0,
          477.0
        ],
        [
          3.0,
          479.0
        ],
        [
          4.0,
          479.0
        ],
        [
          7.0,
          482.0
        ],
        [
          8.0,
          482.0
        ],
        [
          10.0,
          484.0
        ],
        [
          11.0,
          484.0
        ],
        [
          12.0,
          485.0
        ],
        [
          16.0,
          485.0
        ],
        [
          21.0,
          480.0
        ],
        [
          22.0,
          480.0
        ],
        [
          23.0,
          479.0
        ],
        [
          25.0,
          479.0
        ],
        [
          26.0,
          480.0
        ],
        [
          27.0,
          480.0
        ],
        [
          29.0,
          482.0
        ],
        [
          29.0,
          487.0
        ],
        [
          28.0,
          488.0
        ],
        [
          28.0,
          489.0
        ],
        [
          31.0,
          492.0
        ],
        [
          32.0,
          492.0
        ],
        [
          34.0,
          494.0
        ],
        [
          34.0,
          495.0
        ],
        [
          35.0,
          496.0
        ],
        [
          35.0,
          498.0
        ],
        [
          36.0,
          499.0
        ],
        [
          36.0,
          508.0
        ],
        [
          37.0,
          509.0
        ],
        [
          37.0,
          512.0
        ],
        [
          38.0,
          513.0
        ],
        [
          38.0,
          515.0
        ],
        [
          39.0,
          516.0
        ],
        [
          39.0,
          517.0
        ],
        [
          40.0,
          518.0
        ],
        [
          42.0,
          518.0
        ],
        [
          43.0,
          519.0
        ],
        [
          44.0,
          518.0
        ],
        [
          47.0,
          518.0
        ],
        [
          48.0,
          517.0
        ],
        [
          48.0,
          516.0
        ],
        [
          51.0,
          513.0
        ],
        [
          51.0,
          512.0
        ],
        [
          52.0,
          511.0
        ],
        [
          52.0,
          506.0
        ],
        [
          53.0,
          505.0
        ],
        [
          53.0,
          504.0
        ],
        [
          52.0,
          503.0
        ],
        [
          52.0,
          500.0
        ],
        [
          51.0,
          499.0
        ],
        [
          51.0,
          496.0
        ],
        [
          53.0,
          494.0
        ],
        [
          54.0,
          494.0
        ],
        [
          54.0,
          493.0
        ],
        [
          55.0,
          492.0
        ],
        [
          55.0,
          488.0
        ],
        [
          54.0,
          487.0
        ],
        [
          54.0,
          486.0
        ],
        [
          53.0,
          485.0
        ],
        [
          53.0,
          484.0
        ],
        [
          52.0,
          483.0
        ],
        [
          52.0,
          482.0
        ],
        [
          51.0,
          481.0
        ],
        [
          51.0,
          478.0
        ],
        [
          52.0,
          477.0
        ],
        [
          52.0,
          474.0
        ],
        [
          53.0,
          473.0
        ],
        [
          53.0,
          466.0
        ],
        [
          54.0,
          465.0
        ],
        [
          54.0,
          460.0
        ],
        [
          55.0,
          459.0
        ],
        [
          55.0,
          455.0
        ],
        [
          56.0,
          454.0
        ],
        [
          56.0,
          452.0
        ],
        [
          57.0,
          451.0
        ],
        [
          57.0,
          443.0
        ],
        [
          56.0,
          442.0
        ],
        [
          56.0,
          441.0
        ],
        [
          54.0,
          439.0
        ],
        [
          54.0,
          438.0
        ],
        [
          52.0,
          436.0
        ],
        [
          52.0,
          435.0
        ],
        [
          51.0,
          434.0
        ],
        [
          51.0,
          433.0
        ],
        [
          50.0,
          432.0
        ],
        [
          50.0,
          431.0
        ],
        [
          49.0,
          430.0
        ],
        [
          49.0,
          428.0
        ],
        [
          48.0,
          427.0
        ],
        [
          48.0,
          426.0
        ],
        [
          46.0,
          424.0
        ],
        [
          45.0,
          424.0
        ],
        [
          44.0,
          423.0
        ]
      ],
      "group_id": null,
      "shape_type": "polygon",
      "flags": {}
    },
    {
      "label": "potato",
      "text": "",
      "points": [
        [
          27.0,
          562.0
        ],
        [
          22.0,
          562.0
        ],
        [
          20.0,
          564.0
        ],
        [
          20.0,
          568.0
        ],
        [
          21.0,
          569.0
        ],
        [
          21.0,
          571.0
        ],
        [
          22.0,
          572.0
        ],
        [
          22.0,
          574.0
        ],
        [
          23.0,
          575.0
        ],
        [
          23.0,
          577.0
        ],
        [
          22.0,
          578.0
        ],
        [
          22.0,
          579.0
        ],
        [
          21.0,
          580.0
        ],
        [
          20.0,
          580.0
        ],
        [
          16.0,
          584.0
        ],
        [
          15.0,
          584.0
        ],
        [
          12.0,
          587.0
        ],
        [
          11.0,
          587.0
        ],
        [
          10.0,
          588.0
        ],
        [
          9.0,
          588.0
        ],
        [
          8.0,
          589.0
        ],
        [
          7.0,
          589.0
        ],
        [
          3.0,
          593.0
        ],
        [
          3.0,
          594.0
        ],
        [
          2.0,
          595.0
        ],
        [
          0.0,
          595.0
        ],
        [
          0.0,
          619.0
        ],
        [
          10.0,
          619.0
        ],
        [
          11.0,
          620.0
        ],
        [
          12.0,
          620.0
        ],
        [
          17.0,
          625.0
        ],
        [
          23.0,
          625.0
        ],
        [
          24.0,
          624.0
        ],
        [
          25.0,
          624.0
        ],
        [
          28.0,
          621.0
        ],
        [
          29.0,
          621.0
        ],
        [
          31.0,
          619.0
        ],
        [
          36.0,
          619.0
        ],
        [
          37.0,
          618.0
        ],
        [
          40.0,
          618.0
        ],
        [
          44.0,
          614.0
        ],
        [
          44.0,
          613.0
        ],
        [
          45.0,
          612.0
        ],
        [
          45.0,
          611.0
        ],
        [
          46.0,
          610.0
        ],
        [
          46.0,
          607.0
        ],
        [
          45.0,
          606.0
        ],
        [
          45.0,
          597.0
        ],
        [
          46.0,
          596.0
        ],
        [
          46.0,
          594.0
        ],
        [
          48.0,
          592.0
        ],
        [
          50.0,
          592.0
        ],
        [
          51.0,
          591.0
        ],
        [
          53.0,
          591.0
        ],
        [
          55.0,
          589.0
        ],
        [
          55.0,
          583.0
        ],
        [
          52.0,
          580.0
        ],
        [
          51.0,
          580.0
        ],
        [
          48.0,
          577.0
        ],
        [
          48.0,
          575.0
        ],
        [
          47.0,
          574.0
        ],
        [
          47.0,
          572.0
        ],
        [
          43.0,
          568.0
        ],
        [
          42.0,
          568.0
        ],
        [
          41.0,
          567.0
        ],
        [
          33.0,
          567.0
        ],
        [
          29.0,
          563.0
        ],
        [
          28.0,
          563.0
        ]
      ],
      "group_id": null,
      "shape_type": "polygon",
      "flags": {}
    },
    {
      "label": "potato",
      "text": "",
      "points": [
        [
          300.0,
          496.0
        ],
        [
          299.0,
          497.0
        ],
        [
          296.0,
          498.0
        ],
        [
          295.0,
          499.0
        ],
        [
          295.0,
          500.0
        ],
        [
          291.0,
          504.0
        ],
        [
          291.0,
          512.0
        ],
        [
          293.0,
          515.0
        ],
        [
          293.0,
          520.0
        ],
        [
          291.0,
          522.0
        ],
        [
          286.0,
          520.0
        ],
        [
          279.0,
          514.0
        ],
        [
          276.0,
          514.0
        ],
        [
          275.0,
          513.0
        ],
        [
          274.0,
          513.0
        ],
        [
          273.0,
          514.0
        ],
        [
          271.0,
          514.0
        ],
        [
          270.0,
          515.0
        ],
        [
          269.0,
          515.0
        ],
        [
          269.0,
          521.0
        ],
        [
          270.0,
          522.0
        ],
        [
          269.0,
          523.0
        ],
        [
          269.0,
          525.0
        ],
        [
          268.0,
          526.0
        ],
        [
          268.0,
          539.0
        ],
        [
          267.0,
          540.0
        ],
        [
          267.0,
          541.0
        ],
        [
          264.0,
          544.0
        ],
        [
          264.0,
          545.0
        ],
        [
          260.0,
          549.0
        ],
        [
          260.0,
          550.0
        ],
        [
          259.0,
          551.0
        ],
        [
          259.0,
          557.0
        ],
        [
          264.0,
          560.0
        ],
        [
          267.0,
          560.0
        ],
        [
          268.0,
          561.0
        ],
        [
          272.0,
          561.0
        ],
        [
          273.0,
          562.0
        ],
        [
          279.0,
          562.0
        ],
        [
          280.0,
          561.0
        ],
        [
          286.0,
          561.0
        ],
        [
          288.0,
          563.0
        ],
        [
          288.0,
          565.0
        ],
        [
          289.0,
          566.0
        ],
        [
          289.0,
          572.0
        ],
        [
          290.0,
          573.0
        ],
        [
          290.0,
          577.0
        ],
        [
          291.0,
          578.0
        ],
        [
          293.0,
          578.0
        ],
        [
          294.0,
          579.0
        ],
        [
          299.0,
          579.0
        ],
        [
          300.0,
          578.0
        ],
        [
          301.0,
          578.0
        ],
        [
          303.0,
          576.0
        ],
        [
          303.0,
          575.0
        ],
        [
          308.0,
          570.0
        ],
        [
          310.0,
          570.0
        ],
        [
          314.0,
          573.0
        ],
        [
          314.0,
          574.0
        ],
        [
          316.0,
          576.0
        ],
        [
          318.0,
          581.0
        ],
        [
          323.0,
          586.0
        ],
        [
          327.0,
          586.0
        ],
        [
          328.0,
          585.0
        ],
        [
          333.0,
          583.0
        ],
        [
          335.0,
          581.0
        ],
        [
          335.0,
          573.0
        ],
        [
          338.0,
          569.0
        ],
        [
          341.0,
          569.0
        ],
        [
          342.0,
          568.0
        ],
        [
          349.0,
          568.0
        ],
        [
          350.0,
          567.0
        ],
        [
          352.0,
          567.0
        ],
        [
          356.0,
          563.0
        ],
        [
          357.0,
          563.0
        ],
        [
          359.0,
          560.0
        ],
        [
          359.0,
          559.0
        ],
        [
          358.0,
          558.0
        ],
        [
          358.0,
          556.0
        ],
        [
          357.0,
          555.0
        ],
        [
          356.0,
          555.0
        ],
        [
          353.0,
          553.0
        ],
        [
          352.0,
          553.0
        ],
        [
          349.0,
          555.0
        ],
        [
          346.0,
          555.0
        ],
        [
          344.0,
          553.0
        ],
        [
          341.0,
          552.0
        ],
        [
          336.0,
          547.0
        ],
        [
          336.0,
          546.0
        ],
        [
          335.0,
          545.0
        ],
        [
          335.0,
          544.0
        ],
        [
          336.0,
          543.0
        ],
        [
          336.0,
          541.0
        ],
        [
          337.0,
          540.0
        ],
        [
          343.0,
          538.0
        ],
        [
          349.0,
          532.0
        ],
        [
          350.0,
          532.0
        ],
        [
          356.0,
          527.0
        ],
        [
          356.0,
          526.0
        ],
        [
          357.0,
          525.0
        ],
        [
          357.0,
          516.0
        ],
        [
          354.0,
          513.0
        ],
        [
          348.0,
          513.0
        ],
        [
          347.0,
          514.0
        ],
        [
          342.0,
          514.0
        ],
        [
          341.0,
          515.0
        ],
        [
          339.0,
          515.0
        ],
        [
          337.0,
          517.0
        ],
        [
          336.0,
          517.0
        ],
        [
          334.0,
          519.0
        ],
        [
          333.0,
          519.0
        ],
        [
          330.0,
          516.0
        ],
        [
          330.0,
          515.0
        ],
        [
          329.0,
          514.0
        ],
        [
          326.0,
          513.0
        ],
        [
          324.0,
          511.0
        ],
        [
          319.0,
          511.0
        ],
        [
          318.0,
          512.0
        ],
        [
          316.0,
          512.0
        ],
        [
          313.0,
          509.0
        ],
        [
          313.0,
          507.0
        ],
        [
          312.0,
          506.0
        ],
        [
          312.0,
          505.0
        ],
        [
          309.0,
          502.0
        ],
        [
          309.0,
          501.0
        ],
        [
          307.0,
          499.0
        ]
      ],
      "group_id": null,
      "shape_type": "polygon",
      "flags": {}
    },
    {
      "label": "potato",
      "text": "",
      "points": [
        [
          258.0,
          637.0
        ],
        [
          259.0,
          638.0
        ],
        [
          259.0,
          639.0
        ],
        [
          326.0,
          639.0
        ],
        [
          329.0,
          636.0
        ],
        [
          330.0,
          636.0
        ],
        [
          331.0,
          635.0
        ],
        [
          333.0,
          635.0
        ],
        [
          334.0,
          634.0
        ],
        [
          335.0,
          634.0
        ],
        [
          336.0,
          633.0
        ],
        [
          337.0,
          633.0
        ],
        [
          339.0,
          631.0
        ],
        [
          339.0,
          630.0
        ],
        [
          340.0,
          629.0
        ],
        [
          340.0,
          628.0
        ],
        [
          341.0,
          627.0
        ],
        [
          341.0,
          623.0
        ],
        [
          340.0,
          622.0
        ],
        [
          339.0,
          622.0
        ],
        [
          338.0,
          621.0
        ],
        [
          336.0,
          621.0
        ],
        [
          335.0,
          620.0
        ],
        [
          334.0,
          620.0
        ],
        [
          333.0,
          619.0
        ],
        [
          323.0,
          619.0
        ],
        [
          322.0,
          620.0
        ],
        [
          321.0,
          620.0
        ],
        [
          319.0,
          622.0
        ],
        [
          318.0,
          622.0
        ],
        [
          316.0,
          624.0
        ],
        [
          304.0,
          624.0
        ],
        [
          303.0,
          623.0
        ],
        [
          302.0,
          623.0
        ],
        [
          301.0,
          622.0
        ],
        [
          297.0,
          622.0
        ],
        [
          296.0,
          621.0
        ],
        [
          295.0,
          621.0
        ],
        [
          293.0,
          619.0
        ],
        [
          291.0,
          619.0
        ],
        [
          290.0,
          618.0
        ],
        [
          287.0,
          618.0
        ],
        [
          286.0,
          617.0
        ],
        [
          285.0,
          618.0
        ],
        [
          284.0,
          618.0
        ],
        [
          282.0,
          620.0
        ],
        [
          282.0,
          621.0
        ],
        [
          281.0,
          622.0
        ],
        [
          281.0,
          623.0
        ],
        [
          280.0,
          624.0
        ],
        [
          280.0,
          625.0
        ],
        [
          279.0,
          626.0
        ],
        [
          270.0,
          626.0
        ],
        [
          269.0,
          627.0
        ],
        [
          267.0,
          627.0
        ],
        [
          266.0,
          628.0
        ],
        [
          264.0,
          628.0
        ],
        [
          263.0,
          629.0
        ],
        [
          260.0,
          629.0
        ],
        [
          258.0,
          631.0
        ]
      ],
      "group_id": null,
      "shape_type": "polygon",
      "flags": {}
    },
    {
      "label": "potato",
      "text": "",
      "points": [
        [
          570.0,
          463.0
        ],
        [
          570.0,
          473.0
        ],
        [
          571.0,
          474.0
        ],
        [
          571.0,
          475.0
        ],
        [
          575.0,
          479.0
        ],
        [
          576.0,
          479.0
        ],
        [
          578.0,
          481.0
        ],
        [
          579.0,
          481.0
        ],
        [
          580.0,
          482.0
        ],
        [
          581.0,
          482.0
        ],
        [
          582.0,
          483.0
        ],
        [
          584.0,
          483.0
        ],
        [
          585.0,
          484.0
        ],
        [
          586.0,
          484.0
        ],
        [
          588.0,
          486.0
        ],
        [
          588.0,
          487.0
        ],
        [
          589.0,
          488.0
        ],
        [
          590.0,
          488.0
        ],
        [
          593.0,
          491.0
        ],
        [
          596.0,
          491.0
        ],
        [
          597.0,
          490.0
        ],
        [
          598.0,
          490.0
        ],
        [
          599.0,
          489.0
        ],
        [
          601.0,
          489.0
        ],
        [
          602.0,
          490.0
        ],
        [
          605.0,
          490.0
        ],
        [
          606.0,
          491.0
        ],
        [
          608.0,
          491.0
        ],
        [
          609.0,
          492.0
        ],
        [
          610.0,
          492.0
        ],
        [
          612.0,
          494.0
        ],
        [
          612.0,
          495.0
        ],
        [
          613.0,
          496.0
        ],
        [
          613.0,
          497.0
        ],
        [
          614.0,
          497.0
        ],
        [
          615.0,
          498.0
        ],
        [
          617.0,
          498.0
        ],
        [
          618.0,
          499.0
        ],
        [
          619.0,
          499.0
        ],
        [
          620.0,
          498.0
        ],
        [
          622.0,
          498.0
        ],
        [
          623.0,
          497.0
        ],
        [
          624.0,
          497.0
        ],
        [
          625.0,
          496.0
        ],
        [
          626.0,
          496.0
        ],
        [
          627.0,
          495.0
        ],
        [
          628.0,
          495.0
        ],
        [
          629.0,
          494.0
        ],
        [
          629.0,
          492.0
        ],
        [
          628.0,
          491.0
        ],
        [
          628.0,
          490.0
        ],
        [
          625.0,
          487.0
        ],
        [
          624.0,
          487.0
        ],
        [
          623.0,
          486.0
        ],
        [
          622.0,
          486.0
        ],
        [
          621.0,
          487.0
        ],
        [
          617.0,
          487.0
        ],
        [
          615.0,
          485.0
        ],
        [
          615.0,
          483.0
        ],
        [
          616.0,
          482.0
        ],
        [
          616.0,
          477.0
        ],
        [
          617.0,
          476.0
        ],
        [
          617.0,
          466.0
        ],
        [
          618.0,
          465.0
        ],
        [
          618.0,
          464.0
        ],
        [
          619.0,
          463.0
        ],
        [
          619.0,
          462.0
        ],
        [
          620.0,
          461.0
        ],
        [
          620.0,
          458.0
        ],
        [
          619.0,
          457.0
        ],
        [
          619.0,
          456.0
        ],
        [
          618.0,
          455.0
        ],
        [
          618.0,
          454.0
        ],
        [
          617.0,
          453.0
        ],
        [
          617.0,
          452.0
        ],
        [
          615.0,
          450.0
        ],
        [
          614.0,
          450.0
        ],
        [
          613.0,
          449.0
        ],
        [
          606.0,
          449.0
        ],
        [
          605.0,
          450.0
        ],
        [
          604.0,
          450.0
        ],
        [
          601.0,
          453.0
        ],
        [
          600.0,
          453.0
        ],
        [
          597.0,
          450.0
        ],
        [
          595.0,
          450.0
        ],
        [
          594.0,
          449.0
        ],
        [
          586.0,
          449.0
        ],
        [
          585.0,
          450.0
        ],
        [
          583.0,
          450.0
        ],
        [
          581.0,
          452.0
        ],
        [
          581.0,
          453.0
        ],
        [
          578.0,
          456.0
        ],
        [
          578.0,
          457.0
        ],
        [
          574.0,
          461.0
        ],
        [
          572.0,
          461.0
        ]
      ],
      "group_id": null,
      "shape_type": "polygon",
      "flags": {}
    },
    {
      "label": "potato",
      "text": "",
      "points": [
        [
          564.0,
          595.0
        ],
        [
          564.0,
          599.0
        ],
        [
          565.0,
          600.0
        ],
        [
          565.0,
          604.0
        ],
        [
          566.0,
          605.0
        ],
        [
          567.0,
          605.0
        ],
        [
          568.0,
          606.0
        ],
        [
          569.0,
          606.0
        ],
        [
          570.0,
          607.0
        ],
        [
          571.0,
          607.0
        ],
        [
          572.0,
          608.0
        ],
        [
          574.0,
          608.0
        ],
        [
          576.0,
          610.0
        ],
        [
          583.0,
          610.0
        ],
        [
          584.0,
          609.0
        ],
        [
          586.0,
          609.0
        ],
        [
          587.0,
          608.0
        ],
        [
          588.0,
          608.0
        ],
        [
          589.0,
          607.0
        ],
        [
          591.0,
          607.0
        ],
        [
          592.0,
          606.0
        ],
        [
          593.0,
          606.0
        ],
        [
          594.0,
          605.0
        ],
        [
          595.0,
          605.0
        ],
        [
          596.0,
          604.0
        ],
        [
          597.0,
          604.0
        ],
        [
          600.0,
          601.0
        ],
        [
          600.0,
          597.0
        ],
        [
          596.0,
          593.0
        ],
        [
          595.0,
          593.0
        ],
        [
          594.0,
          592.0
        ],
        [
          589.0,
          592.0
        ],
        [
          588.0,
          591.0
        ],
        [
          586.0,
          591.0
        ],
        [
          585.0,
          590.0
        ],
        [
          581.0,
          590.0
        ],
        [
          580.0,
          589.0
        ],
        [
          577.0,
          589.0
        ],
        [
          576.0,
          588.0
        ],
        [
          570.0,
          588.0
        ],
        [
          569.0,
          589.0
        ],
        [
          568.0,
          589.0
        ],
        [
          565.0,
          592.0
        ],
        [
          565.0,
          594.0
        ]
      ],
      "group_id": null,
      "shape_type": "polygon",
      "flags": {}
    },
    {
      "label": "weed",
      "text": "",
      "points": [
        [
          393.0,
          451.0
        ],
        [
          392.0,
          451.0
        ],
        [
          391.0,
          450.0
        ],
        [
          389.0,
          450.0
        ],
        [
          388.0,
          449.0
        ],
        [
          383.0,
          449.0
        ],
        [
          382.0,
          450.0
        ],
        [
          380.0,
          450.0
        ],
        [
          379.0,
          451.0
        ],
        [
          378.0,
          451.0
        ],
        [
          377.0,
          452.0
        ],
        [
          376.0,
          452.0
        ],
        [
          375.0,
          453.0
        ],
        [
          373.0,
          453.0
        ],
        [
          372.0,
          454.0
        ],
        [
          371.0,
          454.0
        ],
        [
          371.0,
          455.0
        ],
        [
          370.0,
          456.0
        ],
        [
          370.0,
          462.0
        ],
        [
          371.0,
          463.0
        ],
        [
          371.0,
          464.0
        ],
        [
          373.0,
          466.0
        ],
        [
          373.0,
          467.0
        ],
        [
          374.0,
          467.0
        ],
        [
          376.0,
          469.0
        ],
        [
          377.0,
          469.0
        ],
        [
          379.0,
          471.0
        ],
        [
          383.0,
          471.0
        ],
        [
          384.0,
          470.0
        ],
        [
          384.0,
          469.0
        ],
        [
          387.0,
          466.0
        ],
        [
          388.0,
          466.0
        ],
        [
          390.0,
          464.0
        ],
        [
          391.0,
          464.0
        ],
        [
          395.0,
          460.0
        ],
        [
          396.0,
          460.0
        ],
        [
          397.0,
          459.0
        ],
        [
          397.0,
          455.0
        ]
      ],
      "group_id": null,
      "shape_type": "polygon",
      "flags": {}
    },
    {
      "label": "weed",
      "text": "",
      "points": [
        [
          522.0,
          468.0
        ],
        [
          517.0,
          468.0
        ],
        [
          516.0,
          469.0
        ],
        [
          514.0,
          469.0
        ],
        [
          513.0,
          470.0
        ],
        [
          506.0,
          470.0
        ],
        [
          505.0,
          471.0
        ],
        [
          504.0,
          471.0
        ],
        [
          504.0,
          472.0
        ],
        [
          503.0,
          473.0
        ],
        [
          503.0,
          474.0
        ],
        [
          502.0,
          475.0
        ],
        [
          502.0,
          477.0
        ],
        [
          501.0,
          478.0
        ],
        [
          501.0,
          482.0
        ],
        [
          499.0,
          484.0
        ],
        [
          499.0,
          491.0
        ],
        [
          500.0,
          492.0
        ],
        [
          500.0,
          494.0
        ],
        [
          498.0,
          496.0
        ],
        [
          498.0,
          497.0
        ],
        [
          500.0,
          499.0
        ],
        [
          502.0,
          499.0
        ],
        [
          503.0,
          500.0
        ],
        [
          504.0,
          500.0
        ],
        [
          505.0,
          501.0
        ],
        [
          508.0,
          501.0
        ],
        [
          510.0,
          499.0
        ],
        [
          510.0,
          498.0
        ],
        [
          511.0,
          497.0
        ],
        [
          512.0,
          497.0
        ],
        [
          513.0,
          496.0
        ],
        [
          515.0,
          496.0
        ],
        [
          517.0,
          498.0
        ],
        [
          520.0,
          498.0
        ],
        [
          521.0,
          497.0
        ],
        [
          521.0,
          491.0
        ],
        [
          522.0,
          490.0
        ],
        [
          522.0,
          478.0
        ],
        [
          523.0,
          477.0
        ],
        [
          523.0,
          475.0
        ],
        [
          524.0,
          474.0
        ],
        [
          524.0,
          470.0
        ]
      ],
      "group_id": null,
      "shape_type": "polygon",
      "flags": {}
    },
    {
      "label": "weed",
      "text": "",
      "points": [
        [
          600.0,
          280.0
        ],
        [
          597.0,
          280.0
        ],
        [
          596.0,
          281.0
        ],
        [
          594.0,
          281.0
        ],
        [
          590.0,
          285.0
        ],
        [
          590.0,
          286.0
        ],
        [
          586.0,
          290.0
        ],
        [
          586.0,
          292.0
        ],
        [
          585.0,
          293.0
        ],
        [
          585.0,
          300.0
        ],
        [
          588.0,
          303.0
        ],
        [
          589.0,
          303.0
        ],
        [
          590.0,
          304.0
        ],
        [
          596.0,
          304.0
        ],
        [
          597.0,
          303.0
        ],
        [
          599.0,
          303.0
        ],
        [
          600.0,
          302.0
        ],
        [
          605.0,
          302.0
        ],
        [
          605.0,
          298.0
        ],
        [
          607.0,
          296.0
        ],
        [
          607.0,
          292.0
        ],
        [
          606.0,
          291.0
        ],
        [
          606.0,
          289.0
        ],
        [
          605.0,
          288.0
        ],
        [
          605.0,
          287.0
        ],
        [
          604.0,
          286.0
        ],
        [
          604.0,
          284.0
        ]
      ],
      "group_id": null,
      "shape_type": "polygon",
      "flags": {}
    },
    {
      "label": "weed",
      "text": "",
      "points": [
        [
          259.0,
          100.0
        ],
        [
          258.0,
          101.0
        ],
        [
          256.0,
          101.0
        ],
        [
          254.0,
          103.0
        ],
        [
          254.0,
          105.0
        ],
        [
          253.0,
          106.0
        ],
        [
          253.0,
          107.0
        ],
        [
          254.0,
          108.0
        ],
        [
          254.0,
          111.0
        ],
        [
          255.0,
          112.0
        ],
        [
          255.0,
          113.0
        ],
        [
          256.0,
          114.0
        ],
        [
          256.0,
          115.0
        ],
        [
          257.0,
          116.0
        ],
        [
          257.0,
          117.0
        ],
        [
          263.0,
          117.0
        ],
        [
          264.0,
          116.0
        ],
        [
          266.0,
          116.0
        ],
        [
          268.0,
          114.0
        ],
        [
          269.0,
          114.0
        ],
        [
          271.0,
          112.0
        ],
        [
          271.0,
          111.0
        ],
        [
          272.0,
          110.0
        ],
        [
          272.0,
          109.0
        ],
        [
          271.0,
          108.0
        ],
        [
          271.0,
          107.0
        ],
        [
          269.0,
          105.0
        ],
        [
          269.0,
          104.0
        ],
        [
          268.0,
          103.0
        ],
        [
          268.0,
          102.0
        ],
        [
          267.0,
          101.0
        ],
        [
          265.0,
          101.0
        ],
        [
          264.0,
          100.0
        ]
      ],
      "group_id": null,
      "shape_type": "polygon",
      "flags": {}
    }
  ],
  "imagePath": "..\\after_crop\\tile_4_5.jpg",
  "imageData": null,
  "imageHeight": 640,
  "imageWidth": 640
}